[
    "ZTE KK",
    "Soproni Tigrisek",
    "Soproni Sportiskola",
    "Soproni Darazsak",
    "Budapesti Honved",
    "Falco"
]

{
    "short name" : "ZTE KK",
    "full name" : "Zalaegerszegi Kosarlabda Klub",
    "hometown" : "Zalaegerszeg",
    "players" : [
        "Kiss Jozsef",
        "Szabo Laszlo",
        "Nemeth Valentin",
        "Makkos David",
        "Kiss Barnabas",
        "James Kinney"
    ]
}


{
    "position" : "center",
    "number" : 15,
    "points" : {
        "2021": 23,
        "2020" : 43,
        "2019" : 123
    },
    "birthdate": "1992.02.45.",
    "height": 134.5
}



{
    "height" : 123.4
}

{
    "birthdate": "1992.02.45.",
    "height" : 123.4,
    "number" : 15,
    "height measurement unit": "cm"
}

{
    "birthdate": "1992.02.45.",
    "number" : 15,
    "height" : {
        "value" : 123.4,
        "measurement unit": "cm",
        "date" : "2020.02.20."
    }
}


